[
  {
    "id": "R00",
    "orientation": 1.2699999809265137,
    "lon": 13.41907024383545,
    "address": "0, 13, a2, 0, 40, 99, f0, ee",
    "keySet": [
      "2",
      "3",
      "e",
      "w",
      "q"
    ],
    "midiChannel": 0,
    "lat": 52.4963493347168
  },
  {
    "id": "R11",
    "orientation": 0.5899998545646667,
    "lon": 13.419757843017578,
    "address": "0, 13, a2, 0, 40, 99, 5c, 2",
    "keySet": [
      "2",
      "3",
      "e",
      "w",
      "q"
    ],
    "midiChannel": 0,
    "lat": 52.495513916015625
  },
  {
    "id": "R22",
    "orientation": 4.210000038146973,
    "lon": 13.421259880065918,
    "address": "0, 13, a2, 0, 40, 9e, ec, d3",
    "keySet": [
      "2",
      "3",
      "e",
      "w",
      "q"
    ],
    "midiChannel": 0,
    "lat": 52.49608612060547
  },
  {
    "id": "R33",
    "orientation": 3.3499982357025146,
    "lon": 13.420014381408691,
    "address": "0, 13, a2, 0, 40, 9e, ec, cd",
    "keySet": [
      "2",
      "3",
      "e",
      "w",
      "q"
    ],
    "midiChannel": 0,
    "lat": 52.49654006958008
  },
  {
    "id": "R44",
    "orientation": -0.5399999618530273,
    "lon": 13.421773910522461,
    "address": "0, 13, a2, 0, 40, 9e, ec, 92",
    "keySet": [
      "2",
      "3",
      "e",
      "w",
      "q"
    ],
    "midiChannel": 0,
    "lat": 52.495445251464844
  }
]